[
  {
    "id": "5465",
    "name": "पाल्हीनन्दन गाउँपालिका",
    "name_en": "Palhinandan Rural Municipality"
  },
  {
    "id": "5466",
    "name": "प्रतापपुर गाउँपालिका",
    "name_en": "Pratappur Rural Municipality"
  },
  {
    "id": "5467",
    "name": "बर्दघाट नगरपालिका",
    "name_en": "Bardaghat Municipality"
  },
  {
    "id": "5471",
    "name": "रामग्राम नगरपालिका",
    "name_en": "Ramgram Municipality"
  },
  {
    "id": "5473",
    "name": "सरावल गाउँपालिका",
    "name_en": "Sarawal Rural Municipality"
  },
  {
    "id": "5474",
    "name": "सुनवल नगरपालिका",
    "name_en": "Sunwal Municipality"
  },
  {
    "id": "5463",
    "name": "सुस्ता गाउँपालिका",
    "name_en": "Susta Rural Municipality"
  }
]
