[
  {
    "id": "5069",
    "name": "चौबिसे गाउँपालिका",
    "name_en": "Chaubise Rural Municipality"
  },
  {
    "id": "5070",
    "name": "छथर जोरपाटी गाउँपालिका",
    "name_en": "Chhathar Jorpati Rural Municipality"
  },
  {
    "id": "5071",
    "name": "धनकुटा नगरपालिका",
    "name_en": "Dhankuta Municipality"
  },
  {
    "id": "5072",
    "name": "पाख्रिवास नगरपालिका",
    "name_en": "Pakhribas Municipality"
  },
  {
    "id": "5073",
    "name": "महालक्ष्मी नगरपालिका",
    "name_en": "Mahalakshmi Municipality"
  },
  {
    "id": "5068",
    "name": "सहिदभूमि गाउँपालिका",
    "name_en": "Sahidbhumi Rural Municipality"
  },
  {
    "id": "5074",
    "name": "साँगुरीगढी गाउँपालिका",
    "name_en": "Sangurigadhi Rural Municipality"
  }
]
